Workbook

Sheet READ ME
A1: T776 Rental Books — free partial sample
A2: A reduced extract of the paid workbook, filled with invented example figures.
C3: What this file is
C4: This is a partial sample of T776 Rental Books, the paid Excel workbook for Canadian landlords who file Form T776. It is not the workbook. It carries the paid file's own header rows and its T776 Summary arithmetic, cut down to two properties and a handful of rows so you can watch the summary compute before you buy.
C5: Every figure here is invented
C6: The amounts on the Rent Ledger, Expenses and T776 Summary tabs are made-up example data, written only to show the arithmetic. None of it is a claim about what the workbook will show for your property, and none of it is a savings claim.
C7: What the paid workbook has that this sample does not
B8: Tabs | C8: The paid file has eight: START HERE, Setup, Rent Ledger, Expenses, Mileage, T776 Summary, Capital & CCA, T776 Codes. This sample carries four of them — Setup, Rent Ledger, Expenses, T776 Summary — plus this page in place of START HERE.
B9: Capacity | C9: The paid file holds 10 properties, 500 ledger rows, 500 expense rows and 250 mileage rows. This sample holds 2 properties and 8 + 8 rows.
B10: Mileage | C10: The paid file's Mileage tab applies CRA's per-kilometre rate and feeds line 9281. There is no Mileage tab here.
B11: Capital & CCA | C11: The paid file keeps rows flagged Capital out of the summary and lists them on a Capital & CCA tab for your accountant. This sample has neither.
B12: Drop-downs | C12: On the paid file the Expense T776-line, property, receipt and repair-or-capital cells are drop-downs driven by the T776 Codes tab. Here they are plain text so the file stays small.
C13: How to try it
C14: Type into the shaded cells on the Setup, Rent Ledger and Expenses tabs. The T776 Summary tab totals itself — gross rents and each expense line, per property and per CRA line number, then Amount A, the line-9949 personal portion, deductible expenses and the line-9369 net. Press F9 to recalculate. The tax year is the one cell, B2 on the T776 Summary tab.
C15: Disclaimer
C16: T776 Rental Books is a bookkeeping aid. It is not tax, legal, or accounting advice. Check your categories and allocations with a qualified accountant.
C17: Partial free sample of T776 Rental Books, version 1.0. Example data invented for this file.

Sheet Setup
A1: Setup
A2: One row per property. Sample: two properties. (Paid file: ten.)
A4: Property ID | B4: Property name | C4: Address | D4: Province | E4: Your ownership % | F4: Date acquired | G4: Rental use % | H4: Notes
A5: P1 | B5: Maple St duplex | C5: 12 Maple St, Example ON | D5: ON | E5: 1 | F5: 2019-06-01 | G5: 1 | H5: Both units rented all year. Example row.
A6: P2 | B6: Basement suite (own home) | C6: 88 Example Ave, Example ON | D6: ON | E6: 1 | F6: 2021-09-01 | G6: 0.4 | H6: Suite in the owner's home; 40% of the home's costs are the rental share. Example row.
A8: Paid file: ten property rows (P1–P10). The property IDs above are referenced by every other tab.

Sheet Rent Ledger
A1: Rent Ledger
A2: Log rent as you receive it. Example rows only — invented amounts.
J3: Year | K3: ='T776 Summary'!$B$2
A4: Date received | B4: Property ID | C4: Unit | D4: Tenant | E4: Month (auto) | F4: Amount due | G4: Amount received | H4: Payment method | I4: Notes | J4: Rent received by property and month | K4: Jan | L4: Feb | M4: Mar | N4: Apr | O4: May | P4: Jun | Q4: Jul | R4: Aug | S4: Sep | T4: Oct | U4: Nov | V4: Dec | W4: Total
A5: 45660 | B5: P1 | C5: Upper | D5: Example tenant A | E5: =IF($A5="","",TEXT($A5,"YYYY-MM")) | F5: 1850 | G5: 1850 | H5: e-Transfer | I5: Example row | J5: =Setup!$A5 | K5: =SUMIFS($G$5:$G$12,$B$5:$B$12,$J5,$E$5:$E$12,TEXT(DATE($K$3,1,1),"YYYY-MM")) | L5: =SUMIFS($G$5:$G$12,$B$5:$B$12,$J5,$E$5:$E$12,TEXT(DATE($K$3,2,1),"YYYY-MM")) | M5: =SUMIFS($G$5:$G$12,$B$5:$B$12,$J5,$E$5:$E$12,TEXT(DATE($K$3,3,1),"YYYY-MM")) | N5: =SUMIFS($G$5:$G$12,$B$5:$B$12,$J5,$E$5:$E$12,TEXT(DATE($K$3,4,1),"YYYY-MM")) | O5: =SUMIFS($G$5:$G$12,$B$5:$B$12,$J5,$E$5:$E$12,TEXT(DATE($K$3,5,1),"YYYY-MM")) | P5: =SUMIFS($G$5:$G$12,$B$5:$B$12,$J5,$E$5:$E$12,TEXT(DATE($K$3,6,1),"YYYY-MM")) | Q5: =SUMIFS($G$5:$G$12,$B$5:$B$12,$J5,$E$5:$E$12,TEXT(DATE($K$3,7,1),"YYYY-MM")) | R5: =SUMIFS($G$5:$G$12,$B$5:$B$12,$J5,$E$5:$E$12,TEXT(DATE($K$3,8,1),"YYYY-MM")) | S5: =SUMIFS($G$5:$G$12,$B$5:$B$12,$J5,$E$5:$E$12,TEXT(DATE($K$3,9,1),"YYYY-MM")) | T5: =SUMIFS($G$5:$G$12,$B$5:$B$12,$J5,$E$5:$E$12,TEXT(DATE($K$3,10,1),"YYYY-MM")) | U5: =SUMIFS($G$5:$G$12,$B$5:$B$12,$J5,$E$5:$E$12,TEXT(DATE($K$3,11,1),"YYYY-MM")) | V5: =SUMIFS($G$5:$G$12,$B$5:$B$12,$J5,$E$5:$E$12,TEXT(DATE($K$3,12,1),"YYYY-MM")) | W5: =SUM(K5:V5)
A6: 45660 | B6: P1 | C6: Lower | D6: Example tenant B | E6: =IF($A6="","",TEXT($A6,"YYYY-MM")) | F6: 1500 | G6: 1500 | H6: Pre-authorized debit | I6: Example row | J6: =Setup!$A6 | K6: =SUMIFS($G$5:$G$12,$B$5:$B$12,$J6,$E$5:$E$12,TEXT(DATE($K$3,1,1),"YYYY-MM")) | L6: =SUMIFS($G$5:$G$12,$B$5:$B$12,$J6,$E$5:$E$12,TEXT(DATE($K$3,2,1),"YYYY-MM")) | M6: =SUMIFS($G$5:$G$12,$B$5:$B$12,$J6,$E$5:$E$12,TEXT(DATE($K$3,3,1),"YYYY-MM")) | N6: =SUMIFS($G$5:$G$12,$B$5:$B$12,$J6,$E$5:$E$12,TEXT(DATE($K$3,4,1),"YYYY-MM")) | O6: =SUMIFS($G$5:$G$12,$B$5:$B$12,$J6,$E$5:$E$12,TEXT(DATE($K$3,5,1),"YYYY-MM")) | P6: =SUMIFS($G$5:$G$12,$B$5:$B$12,$J6,$E$5:$E$12,TEXT(DATE($K$3,6,1),"YYYY-MM")) | Q6: =SUMIFS($G$5:$G$12,$B$5:$B$12,$J6,$E$5:$E$12,TEXT(DATE($K$3,7,1),"YYYY-MM")) | R6: =SUMIFS($G$5:$G$12,$B$5:$B$12,$J6,$E$5:$E$12,TEXT(DATE($K$3,8,1),"YYYY-MM")) | S6: =SUMIFS($G$5:$G$12,$B$5:$B$12,$J6,$E$5:$E$12,TEXT(DATE($K$3,9,1),"YYYY-MM")) | T6: =SUMIFS($G$5:$G$12,$B$5:$B$12,$J6,$E$5:$E$12,TEXT(DATE($K$3,10,1),"YYYY-MM")) | U6: =SUMIFS($G$5:$G$12,$B$5:$B$12,$J6,$E$5:$E$12,TEXT(DATE($K$3,11,1),"YYYY-MM")) | V6: =SUMIFS($G$5:$G$12,$B$5:$B$12,$J6,$E$5:$E$12,TEXT(DATE($K$3,12,1),"YYYY-MM")) | W6: =SUM(K6:V6)
A7: 45691 | B7: P1 | C7: Upper | D7: Example tenant A | E7: =IF($A7="","",TEXT($A7,"YYYY-MM")) | F7: 1850 | G7: 1850 | H7: e-Transfer | I7: Example row | J7: Total | K7: =SUM(K5:K6) | L7: =SUM(L5:L6) | M7: =SUM(M5:M6) | N7: =SUM(N5:N6) | O7: =SUM(O5:O6) | P7: =SUM(P5:P6) | Q7: =SUM(Q5:Q6) | R7: =SUM(R5:R6) | ... W7: =SUM(W5:W6)
A8: 45691 | B8: P1 | C8: Lower | D8: Example tenant B | E8: =IF($A8="","",TEXT($A8,"YYYY-MM")) | F8: 1500 | G8: 1500 | H8: Pre-authorized debit | I8: Example row
A9: 45717 | B9: P2 | C9: Suite | D9: Example tenant C | E9: =IF($A9="","",TEXT($A9,"YYYY-MM")) | F9: 1150 | G9: 1150 | H9: e-Transfer | I9: Example row | J9: Same monthly grid as the paid file, cut to two properties. The paid grid covers ten.
A10: 45748 | B10: P2 | C10: Suite | D10: Example tenant C | E10: =IF($A10="","",TEXT($A10,"YYYY-MM")) | F10: 1150 | G10: 1150 | H10: e-Transfer | I10: Example row
A11: 45780 | B11: P1 | C11: Upper | D11: Example tenant A | E11: =IF($A11="","",TEXT($A11,"YYYY-MM")) | F11: 1850 | G11: 1850 | H11: e-Transfer | I11: Example row
A12: 45809 | B12: P2 | C12: Suite | D12: Example tenant C | E12: =IF($A12="","",TEXT($A12,"YYYY-MM")) | F12: 1150 | G12: 1150 | H12: e-Transfer | I12: Example row

Sheet Expenses
A1: Expenses
A2: One row per payment, tagged to a T776 line. Example rows only — invented amounts.
M3: Rental share applied
A4: Date paid | B4: Property ID | C4: T776 line | D4: Vendor / payee | E4: Description | F4: Amount | G4: GST/HST paid | H4: Receipt filed | I4: Repair or capital | J4: Rental share % (optional) | K4: Rental share applied | M4: Column K is calculated: leave the Rental share % blank and the property's Rental use % from Setup is applied; type 100% in column J for an expense that is wholly the rental's.
A5: 45702 | B5: P1 | C5: 9180 Property taxes | D5: Example municipality | E5: Property tax, both units | F5: 2400 | G5: 0 | H5: Yes | I5: Repair | K5: =IF($B5="",0,IF($J5<>"",$J5,IFERROR(VLOOKUP($B5,Setup!$A$5:$G$6,7,FALSE),1))) | M5: The P2 rows above show this: P2's rental use is 40%, so its heat/hydro and insurance come into the summary at 40%, and the P2 repair row overrides that with an explicit 40%.
A6: 45738 | B6: P1 | C6: 8960 Repairs and maintenance | D6: Example plumbing | E6: Fix leaking tap, upper unit | F6: 350 | G6: 45.5 | H6: Yes | I6: Repair | K6: =IF($B6="",0,IF($J6<>"",$J6,IFERROR(VLOOKUP($B6,Setup!$A$5:$G$6,7,FALSE),1))) | M6: Repair or capital: the paid file keeps Capital rows out of the summary and lists them on the Capital & CCA tab. Every row in this sample is a Repair.
A7: 45757 | B7: P2 | C7: 9220 Utilities | D7: Example utilities | E7: Heat and hydro, whole home | F7: 1200 | G7: 156 | H7: Yes | I7: Repair | K7: =IF($B7="",0,IF($J7<>"",$J7,IFERROR(VLOOKUP($B7,Setup!$A$5:$G$6,7,FALSE),1)))
A8: 45777 | B8: P2 | C8: 8690 Insurance | D8: Example insurer | E8: Home insurance policy | F8: 900 | G8: 0 | H8: Yes | I8: Repair | K8: =IF($B8="",0,IF($J8<>"",$J8,IFERROR(VLOOKUP($B8,Setup!$A$5:$G$6,7,FALSE),1)))
A9: 45823 | B9: P1 | C9: 8710 Interest and bank charges | D9: Example bank | E9: Mortgage interest (not principal) | F9: 5200 | G9: 0 | H9: Yes | I9: Repair | K9: =IF($B9="",0,IF($J9<>"",$J9,IFERROR(VLOOKUP($B9,Setup!$A$5:$G$6,7,FALSE),1)))
A10: 45870 | B10: P1 | C10: 9270 Other expenses | D10: Example condo corp | E10: Common-area fees | F10: 180 | G10: 0 | H10: No | I10: Repair | K10: =IF($B10="",0,IF($J10<>"",$J10,IFERROR(VLOOKUP($B10,Setup!$A$5:$G$6,7,FALSE),1)))
A11: 45905 | B11: P1 | C11: 8521 Advertising | D11: Example listings site | E11: Vacancy listing fee | F11: 120 | G11: 15.6 | H11: Yes | I11: Repair | K11: =IF($B11="",0,IF($J11<>"",$J11,IFERROR(VLOOKUP($B11,Setup!$A$5:$G$6,7,FALSE),1)))
A12: 45948 | B12: P2 | C12: 8960 Repairs and maintenance | D12: Example handyman | E12: Patch and paint the suite | F12: 260 | G12: 33.8 | H12: Yes | I12: Repair | J12: 0.4 | K12: =IF($B12="",0,IF($J12<>"",$J12,IFERROR(VLOOKUP($B12,Setup!$A$5:$G$6,7,FALSE),1)))

Sheet T776 Summary
A1: T776 Summary
A2: Tax year | B2: 2025 | C2: The single control for the whole workbook.
A4: Line | B4: Description | C4: =Setup!$A$5 | D4: =Setup!$A$6 | E4: Total | F4: Personal portion (9949) | H4: =Setup!$A$5 | I4: =Setup!$A$6
A5: 8141 | B5: Gross rents | C5: =SUMIFS('Rent Ledger'!$G$5:$G$12,'Rent Ledger'!$B$5:$B$12,Setup!$A$5,'Rent Ledger'!$A$5:$A$12,">="&DATE($B$2,1,1),'Rent Ledger'!$A$5:$A$12,"<="&DATE($B$2,12,31)) | D5: =SUMIFS('Rent Ledger'!$G$5:$G$12,'Rent Ledger'!$B$5:$B$12,Setup!$A$6,'Rent Ledger'!$A$5:$A$12,">="&DATE($B$2,1,1),'Rent Ledger'!$A$5:$A$12,"<="&DATE($B$2,12,31)) | E5: =SUM(C5:D5)
A6: 8521 | B6: Advertising | C6: =SUMPRODUCT((LEFT(Expenses!$C$5:$C$12,4)=$A6)*(Expenses!$B$5:$B$12=Setup!$A$5)*(Expenses!$I$5:$I$12<>"Capital")*(Expenses!$A$5:$A$12>=DATE($B$2,1,1))*(Expenses!$A$5:$A$12<=DATE($B$2,12,31))*Expenses!$F$5:$F$12*Expenses!$K$5:$K$12) | D6: =SUMPRODUCT((LEFT(Expenses!$C$5:$C$12,4)=$A6)*(Expenses!$B$5:$B$12=Setup!$A$6)*(Expenses!$I$5:$I$12<>"Capital")*(Expenses!$A$5:$A$12>=DATE($B$2,1,1))*(Expenses!$A$5:$A$12<=DATE($B$2,12,31))*Expenses!$F$5:$F$12*Expenses!$K$5:$K$12) | E6: =SUM(C6:D6) | F6: =SUM(H6:I6)-E6 | H6: =SUMPRODUCT((LEFT(Expenses!$C$5:$C$12,4)=$A6)*(Expenses!$B$5:$B$12=Setup!$A$5)*(Expenses!$I$5:$I$12<>"Capital")*(Expenses!$A$5:$A$12>=DATE($B$2,1,1))*(Expenses!$A$5:$A$12<=DATE($B$2,12,31))*Expenses!$F$5:$F$12) | I6: =SUMPRODUCT((LEFT(Expenses!$C$5:$C$12,4)=$A6)*(Expenses!$B$5:$B$12=Setup!$A$6)*(Expenses!$I$5:$I$12<>"Capital")*(Expenses!$A$5:$A$12>=DATE($B$2,1,1))*(Expenses!$A$5:$A$12<=DATE($B$2,12,31))*Expenses!$F$5:$F$12)
A7: 8690 | B7: Insurance | C7: =SUMPRODUCT((LEFT(Expenses!$C$5:$C$12,4)=$A7)*(Expenses!$B$5:$B$12=Setup!$A$5)*(Expenses!$I$5:$I$12<>"Capital")*(Expenses!$A$5:$A$12>=DATE($B$2,1,1))*(Expenses!$A$5:$A$12<=DATE($B$2,12,31))*Expenses!$F$5:$F$12*Expenses!$K$5:$K$12) | D7: =SUMPRODUCT((LEFT(Expenses!$C$5:$C$12,4)=$A7)*(Expenses!$B$5:$B$12=Setup!$A$6)*(Expenses!$I$5:$I$12<>"Capital")*(Expenses!$A$5:$A$12>=DATE($B$2,1,1))*(Expenses!$A$5:$A$12<=DATE($B$2,12,31))*Expenses!$F$5:$F$12*Expenses!$K$5:$K$12) | E7: =SUM(C7:D7) | F7: =SUM(H7:I7)-E7 | H7: =SUMPRODUCT((LEFT(Expenses!$C$5:$C$12,4)=$A7)*(Expenses!$B$5:$B$12=Setup!$A$5)*(Expenses!$I$5:$I$12<>"Capital")*(Expenses!$A$5:$A$12>=DATE($B$2,1,1))*(Expenses!$A$5:$A$12<=DATE($B$2,12,31))*Expenses!$F$5:$F$12) | I7: =SUMPRODUCT((LEFT(Expenses!$C$5:$C$12,4)=$A7)*(Expenses!$B$5:$B$12=Setup!$A$6)*(Expenses!$I$5:$I$12<>"Capital")*(Expenses!$A$5:$A$12>=DATE($B$2,1,1))*(Expenses!$A$5:$A$12<=DATE($B$2,12,31))*Expenses!$F$5:$F$12)
A8: 8710 | B8: Interest and bank charges | C8: =SUMPRODUCT((LEFT(Expenses!$C$5:$C$12,4)=$A8)*(Expenses!$B$5:$B$12=Setup!$A$5)*(Expenses!$I$5:$I$12<>"Capital")*(Expenses!$A$5:$A$12>=DATE($B$2,1,1))*(Expenses!$A$5:$A$12<=DATE($B$2,12,31))*Expenses!$F$5:$F$12*Expenses!$K$5:$K$12) | D8: =SUMPRODUCT((LEFT(Expenses!$C$5:$C$12,4)=$A8)*(Expenses!$B$5:$B$12=Setup!$A$6)*(Expenses!$I$5:$I$12<>"Capital")*(Expenses!$A$5:$A$12>=DATE($B$2,1,1))*(Expenses!$A$5:$A$12<=DATE($B$2,12,31))*Expenses!$F$5:$F$12*Expenses!$K$5:$K$12) | E8: =SUM(C8:D8) | F8: =SUM(H8:I8)-E8 | H8: =SUMPRODUCT((LEFT(Expenses!$C$5:$C$12,4)=$A8)*(Expenses!$B$5:$B$12=Setup!$A$5)*(Expenses!$I$5:$I$12<>"Capital")*(Expenses!$A$5:$A$12>=DATE($B$2,1,1))*(Expenses!$A$5:$A$12<=DATE($B$2,12,31))*Expenses!$F$5:$F$12) | I8: =SUMPRODUCT((LEFT(Expenses!$C$5:$C$12,4)=$A8)*(Expenses!$B$5:$B$12=Setup!$A$6)*(Expenses!$I$5:$I$12<>"Capital")*(Expenses!$A$5:$A$12>=DATE($B$2,1,1))*(Expenses!$A$5:$A$12<=DATE($B$2,12,31))*Expenses!$F$5:$F$12)
A9: 8810 | B9: Office expenses | C9: =SUMPRODUCT((LEFT(Expenses!$C$5:$C$12,4)=$A9)*(Expenses!$B$5:$B$12=Setup!$A$5)*(Expenses!$I$5:$I$12<>"Capital")*(Expenses!$A$5:$A$12>=DATE($B$2,1,1))*(Expenses!$A$5:$A$12<=DATE($B$2,12,31))*Expenses!$F$5:$F$12*Expenses!$K$5:$K$12) | D9: =SUMPRODUCT((LEFT(Expenses!$C$5:$C$12,4)=$A9)*(Expenses!$B$5:$B$12=Setup!$A$6)*(Expenses!$I$5:$I$12<>"Capital")*(Expenses!$A$5:$A$12>=DATE($B$2,1,1))*(Expenses!$A$5:$A$12<=DATE($B$2,12,31))*Expenses!$F$5:$F$12*Expenses!$K$5:$K$12) | E9: =SUM(C9:D9) | F9: =SUM(H9:I9)-E9 | H9: =SUMPRODUCT((LEFT(Expenses!$C$5:$C$12,4)=$A9)*(Expenses!$B$5:$B$12=Setup!$A$5)*(Expenses!$I$5:$I$12<>"Capital")*(Expenses!$A$5:$A$12>=DATE($B$2,1,1))*(Expenses!$A$5:$A$12<=DATE($B$2,12,31))*Expenses!$F$5:$F$12) | I9: =SUMPRODUCT((LEFT(Expenses!$C$5:$C$12,4)=$A9)*(Expenses!$B$5:$B$12=Setup!$A$6)*(Expenses!$I$5:$I$12<>"Capital")*(Expenses!$A$5:$A$12>=DATE($B$2,1,1))*(Expenses!$A$5:$A$12<=DATE($B$2,12,31))*Expenses!$F$5:$F$12)
A10: 8860 | B10: Professional fees | C10: =SUMPRODUCT((LEFT(Expenses!$C$5:$C$12,4)=$A10)*(Expenses!$B$5:$B$12=Setup!$A$5)*(Expenses!$I$5:$I$12<>"Capital")*(Expenses!$A$5:$A$12>=DATE($B$2,1,1))*(Expenses!$A$5:$A$12<=DATE($B$2,12,31))*Expenses!$F$5:$F$12*Expenses!$K$5:$K$12) | D10: =SUMPRODUCT((LEFT(Expenses!$C$5:$C$12,4)=$A10)*(Expenses!$B$5:$B$12=Setup!$A$6)*(Expenses!$I$5:$I$12<>"Capital")*(Expenses!$A$5:$A$12>=DATE($B$2,1,1))*(Expenses!$A$5:$A$12<=DATE($B$2,12,31))*Expenses!$F$5:$F$12*Expenses!$K$5:$K$12) | E10: =SUM(C10:D10) | F10: =SUM(H10:I10)-E10 | H10: =SUMPRODUCT((LEFT(Expenses!$C$5:$C$12,4)=$A10)*(Expenses!$B$5:$B$12=Setup!$A$5)*(Expenses!$I$5:$I$12<>"Capital")*(Expenses!$A$5:$A$12>=DATE($B$2,1,1))*(Expenses!$A$5:$A$12<=DATE($B$2,12,31))*Expenses!$F$5:$F$12) | I10: =SUMPRODUCT((LEFT(Expenses!$C$5:$C$12,4)=$A10)*(Expenses!$B$5:$B$12=Setup!$A$6)*(Expenses!$I$5:$I$12<>"Capital")*(Expenses!$A$5:$A$12>=DATE($B$2,1,1))*(Expenses!$A$5:$A$12<=DATE($B$2,12,31))*Expenses!$F$5:$F$12)
A11: 8871 | B11: Management and administration fees | C11: =SUMPRODUCT((LEFT(Expenses!$C$5:$C$12,4)=$A11)*(Expenses!$B$5:$B$12=Setup!$A$5)*(Expenses!$I$5:$I$12<>"Capital")*(Expenses!$A$5:$A$12>=DATE($B$2,1,1))*(Expenses!$A$5:$A$12<=DATE($B$2,12,31))*Expenses!$F$5:$F$12*Expenses!$K$5:$K$12) | D11: =SUMPRODUCT((LEFT(Expenses!$C$5:$C$12,4)=$A11)*(Expenses!$B$5:$B$12=Setup!$A$6)*(Expenses!$I$5:$I$12<>"Capital")*(Expenses!$A$5:$A$12>=DATE($B$2,1,1))*(Expenses!$A$5:$A$12<=DATE($B$2,12,31))*Expenses!$F$5:$F$12*Expenses!$K$5:$K$12) | E11: =SUM(C11:D11) | F11: =SUM(H11:I11)-E11 | H11: =SUMPRODUCT((LEFT(Expenses!$C$5:$C$12,4)=$A11)*(Expenses!$B$5:$B$12=Setup!$A$5)*(Expenses!$I$5:$I$12<>"Capital")*(Expenses!$A$5:$A$12>=DATE($B$2,1,1))*(Expenses!$A$5:$A$12<=DATE($B$2,12,31))*Expenses!$F$5:$F$12) | I11: =SUMPRODUCT((LEFT(Expenses!$C$5:$C$12,4)=$A11)*(Expenses!$B$5:$B$12=Setup!$A$6)*(Expenses!$I$5:$I$12<>"Capital")*(Expenses!$A$5:$A$12>=DATE($B$2,1,1))*(Expenses!$A$5:$A$12<=DATE($B$2,12,31))*Expenses!$F$5:$F$12)
A12: 8960 | B12: Repairs and maintenance | C12: =SUMPRODUCT((LEFT(Expenses!$C$5:$C$12,4)=$A12)*(Expenses!$B$5:$B$12=Setup!$A$5)*(Expenses!$I$5:$I$12<>"Capital")*(Expenses!$A$5:$A$12>=DATE($B$2,1,1))*(Expenses!$A$5:$A$12<=DATE($B$2,12,31))*Expenses!$F$5:$F$12*Expenses!$K$5:$K$12) | D12: =SUMPRODUCT((LEFT(Expenses!$C$5:$C$12,4)=$A12)*(Expenses!$B$5:$B$12=Setup!$A$6)*(Expenses!$I$5:$I$12<>"Capital")*(Expenses!$A$5:$A$12>=DATE($B$2,1,1))*(Expenses!$A$5:$A$12<=DATE($B$2,12,31))*Expenses!$F$5:$F$12*Expenses!$K$5:$K$12) | E12: =SUM(C12:D12) | F12: =SUM(H12:I12)-E12 | H12: =SUMPRODUCT((LEFT(Expenses!$C$5:$C$12,4)=$A12)*(Expenses!$B$5:$B$12=Setup!$A$5)*(Expenses!$I$5:$I$12<>"Capital")*(Expenses!$A$5:$A$12>=DATE($B$2,1,1))*(Expenses!$A$5:$A$12<=DATE($B$2,12,31))*Expenses!$F$5:$F$12) | I12: =SUMPRODUCT((LEFT(Expenses!$C$5:$C$12,4)=$A12)*(Expenses!$B$5:$B$12=Setup!$A$6)*(Expenses!$I$5:$I$12<>"Capital")*(Expenses!$A$5:$A$12>=DATE($B$2,1,1))*(Expenses!$A$5:$A$12<=DATE($B$2,12,31))*Expenses!$F$5:$F$12)
A13: 9060 | B13: Salaries, wages and benefits | C13: =SUMPRODUCT((LEFT(Expenses!$C$5:$C$12,4)=$A13)*(Expenses!$B$5:$B$12=Setup!$A$5)*(Expenses!$I$5:$I$12<>"Capital")*(Expenses!$A$5:$A$12>=DATE($B$2,1,1))*(Expenses!$A$5:$A$12<=DATE($B$2,12,31))*Expenses!$F$5:$F$12*Expenses!$K$5:$K$12) | D13: =SUMPRODUCT((LEFT(Expenses!$C$5:$C$12,4)=$A13)*(Expenses!$B$5:$B$12=Setup!$A$6)*(Expenses!$I$5:$I$12<>"Capital")*(Expenses!$A$5:$A$12>=DATE($B$2,1,1))*(Expenses!$A$5:$A$12<=DATE($B$2,12,31))*Expenses!$F$5:$F$12*Expenses!$K$5:$K$12) | E13: =SUM(C13:D13) | F13: =SUM(H13:I13)-E13 | H13: =SUMPRODUCT((LEFT(Expenses!$C$5:$C$12,4)=$A13)*(Expenses!$B$5:$B$12=Setup!$A$5)*(Expenses!$I$5:$I$12<>"Capital")*(Expenses!$A$5:$A$12>=DATE($B$2,1,1))*(Expenses!$A$5:$A$12<=DATE($B$2,12,31))*Expenses!$F$5:$F$12) | I13: =SUMPRODUCT((LEFT(Expenses!$C$5:$C$12,4)=$A13)*(Expenses!$B$5:$B$12=Setup!$A$6)*(Expenses!$I$5:$I$12<>"Capital")*(Expenses!$A$5:$A$12>=DATE($B$2,1,1))*(Expenses!$A$5:$A$12<=DATE($B$2,12,31))*Expenses!$F$5:$F$12)
A14: 9180 | B14: Property taxes | C14: =SUMPRODUCT((LEFT(Expenses!$C$5:$C$12,4)=$A14)*(Expenses!$B$5:$B$12=Setup!$A$5)*(Expenses!$I$5:$I$12<>"Capital")*(Expenses!$A$5:$A$12>=DATE($B$2,1,1))*(Expenses!$A$5:$A$12<=DATE($B$2,12,31))*Expenses!$F$5:$F$12*Expenses!$K$5:$K$12) | D14: =SUMPRODUCT((LEFT(Expenses!$C$5:$C$12,4)=$A14)*(Expenses!$B$5:$B$12=Setup!$A$6)*(Expenses!$I$5:$I$12<>"Capital")*(Expenses!$A$5:$A$12>=DATE($B$2,1,1))*(Expenses!$A$5:$A$12<=DATE($B$2,12,31))*Expenses!$F$5:$F$12*Expenses!$K$5:$K$12) | E14: =SUM(C14:D14) | F14: =SUM(H14:I14)-E14 | H14: =SUMPRODUCT((LEFT(Expenses!$C$5:$C$12,4)=$A14)*(Expenses!$B$5:$B$12=Setup!$A$5)*(Expenses!$I$5:$I$12<>"Capital")*(Expenses!$A$5:$A$12>=DATE($B$2,1,1))*(Expenses!$A$5:$A$12<=DATE($B$2,12,31))*Expenses!$F$5:$F$12) | I14: =SUMPRODUCT((LEFT(Expenses!$C$5:$C$12,4)=$A14)*(Expenses!$B$5:$B$12=Setup!$A$6)*(Expenses!$I$5:$I$12<>"Capital")*(Expenses!$A$5:$A$12>=DATE($B$2,1,1))*(Expenses!$A$5:$A$12<=DATE($B$2,12,31))*Expenses!$F$5:$F$12)
A15: 9200 | B15: Travel | C15: =SUMPRODUCT((LEFT(Expenses!$C$5:$C$12,4)=$A15)*(Expenses!$B$5:$B$12=Setup!$A$5)*(Expenses!$I$5:$I$12<>"Capital")*(Expenses!$A$5:$A$12>=DATE($B$2,1,1))*(Expenses!$A$5:$A$12<=DATE($B$2,12,31))*Expenses!$F$5:$F$12*Expenses!$K$5:$K$12) | D15: =SUMPRODUCT((LEFT(Expenses!$C$5:$C$12,4)=$A15)*(Expenses!$B$5:$B$12=Setup!$A$6)*(Expenses!$I$5:$I$12<>"Capital")*(Expenses!$A$5:$A$12>=DATE($B$2,1,1))*(Expenses!$A$5:$A$12<=DATE($B$2,12,31))*Expenses!$F$5:$F$12*Expenses!$K$5:$K$12) | E15: =SUM(C15:D15) | F15: =SUM(H15:I15)-E15 | H15: =SUMPRODUCT((LEFT(Expenses!$C$5:$C$12,4)=$A15)*(Expenses!$B$5:$B$12=Setup!$A$5)*(Expenses!$I$5:$I$12<>"Capital")*(Expenses!$A$5:$A$12>=DATE($B$2,1,1))*(Expenses!$A$5:$A$12<=DATE($B$2,12,31))*Expenses!$F$5:$F$12) | I15: =SUMPRODUCT((LEFT(Expenses!$C$5:$C$12,4)=$A15)*(Expenses!$B$5:$B$12=Setup!$A$6)*(Expenses!$I$5:$I$12<>"Capital")*(Expenses!$A$5:$A$12>=DATE($B$2,1,1))*(Expenses!$A$5:$A$12<=DATE($B$2,12,31))*Expenses!$F$5:$F$12)
A16: 9220 | B16: Utilities | C16: =SUMPRODUCT((LEFT(Expenses!$C$5:$C$12,4)=$A16)*(Expenses!$B$5:$B$12=Setup!$A$5)*(Expenses!$I$5:$I$12<>"Capital")*(Expenses!$A$5:$A$12>=DATE($B$2,1,1))*(Expenses!$A$5:$A$12<=DATE($B$2,12,31))*Expenses!$F$5:$F$12*Expenses!$K$5:$K$12) | D16: =SUMPRODUCT((LEFT(Expenses!$C$5:$C$12,4)=$A16)*(Expenses!$B$5:$B$12=Setup!$A$6)*(Expenses!$I$5:$I$12<>"Capital")*(Expenses!$A$5:$A$12>=DATE($B$2,1,1))*(Expenses!$A$5:$A$12<=DATE($B$2,12,31))*Expenses!$F$5:$F$12*Expenses!$K$5:$K$12) | E16: =SUM(C16:D16) | F16: =SUM(H16:I16)-E16 | H16: =SUMPRODUCT((LEFT(Expenses!$C$5:$C$12,4)=$A16)*(Expenses!$B$5:$B$12=Setup!$A$5)*(Expenses!$I$5:$I$12<>"Capital")*(Expenses!$A$5:$A$12>=DATE($B$2,1,1))*(Expenses!$A$5:$A$12<=DATE($B$2,12,31))*Expenses!$F$5:$F$12) | I16: =SUMPRODUCT((LEFT(Expenses!$C$5:$C$12,4)=$A16)*(Expenses!$B$5:$B$12=Setup!$A$6)*(Expenses!$I$5:$I$12<>"Capital")*(Expenses!$A$5:$A$12>=DATE($B$2,1,1))*(Expenses!$A$5:$A$12<=DATE($B$2,12,31))*Expenses!$F$5:$F$12)
A17: 9281 | B17: Motor vehicle expenses | C17: =SUMPRODUCT((LEFT(Expenses!$C$5:$C$12,4)=$A17)*(Expenses!$B$5:$B$12=Setup!$A$5)*(Expenses!$I$5:$I$12<>"Capital")*(Expenses!$A$5:$A$12>=DATE($B$2,1,1))*(Expenses!$A$5:$A$12<=DATE($B$2,12,31))*Expenses!$F$5:$F$12*Expenses!$K$5:$K$12) | D17: =SUMPRODUCT((LEFT(Expenses!$C$5:$C$12,4)=$A17)*(Expenses!$B$5:$B$12=Setup!$A$6)*(Expenses!$I$5:$I$12<>"Capital")*(Expenses!$A$5:$A$12>=DATE($B$2,1,1))*(Expenses!$A$5:$A$12<=DATE($B$2,12,31))*Expenses!$F$5:$F$12*Expenses!$K$5:$K$12) | E17: =SUM(C17:D17) | F17: =SUM(H17:I17)-E17 | H17: =SUMPRODUCT((LEFT(Expenses!$C$5:$C$12,4)=$A17)*(Expenses!$B$5:$B$12=Setup!$A$5)*(Expenses!$I$5:$I$12<>"Capital")*(Expenses!$A$5:$A$12>=DATE($B$2,1,1))*(Expenses!$A$5:$A$12<=DATE($B$2,12,31))*Expenses!$F$5:$F$12) | I17: =SUMPRODUCT((LEFT(Expenses!$C$5:$C$12,4)=$A17)*(Expenses!$B$5:$B$12=Setup!$A$6)*(Expenses!$I$5:$I$12<>"Capital")*(Expenses!$A$5:$A$12>=DATE($B$2,1,1))*(Expenses!$A$5:$A$12<=DATE($B$2,12,31))*Expenses!$F$5:$F$12)
A18: 9270 | B18: Other expenses | C18: =SUMPRODUCT((LEFT(Expenses!$C$5:$C$12,4)=$A18)*(Expenses!$B$5:$B$12=Setup!$A$5)*(Expenses!$I$5:$I$12<>"Capital")*(Expenses!$A$5:$A$12>=DATE($B$2,1,1))*(Expenses!$A$5:$A$12<=DATE($B$2,12,31))*Expenses!$F$5:$F$12*Expenses!$K$5:$K$12) | D18: =SUMPRODUCT((LEFT(Expenses!$C$5:$C$12,4)=$A18)*(Expenses!$B$5:$B$12=Setup!$A$6)*(Expenses!$I$5:$I$12<>"Capital")*(Expenses!$A$5:$A$12>=DATE($B$2,1,1))*(Expenses!$A$5:$A$12<=DATE($B$2,12,31))*Expenses!$F$5:$F$12*Expenses!$K$5:$K$12) | E18: =SUM(C18:D18) | F18: =SUM(H18:I18)-E18 | H18: =SUMPRODUCT((LEFT(Expenses!$C$5:$C$12,4)=$A18)*(Expenses!$B$5:$B$12=Setup!$A$5)*(Expenses!$I$5:$I$12<>"Capital")*(Expenses!$A$5:$A$12>=DATE($B$2,1,1))*(Expenses!$A$5:$A$12<=DATE($B$2,12,31))*Expenses!$F$5:$F$12) | I18: =SUMPRODUCT((LEFT(Expenses!$C$5:$C$12,4)=$A18)*(Expenses!$B$5:$B$12=Setup!$A$6)*(Expenses!$I$5:$I$12<>"Capital")*(Expenses!$A$5:$A$12>=DATE($B$2,1,1))*(Expenses!$A$5:$A$12<=DATE($B$2,12,31))*Expenses!$F$5:$F$12)
A19: A | B19: Amount A - total expenses, before the personal-use adjustment | E19: =E6+E7+E8+E9+E10+E11+E12+E13+E14+E15+E16+E17+E18+F6+F7+F8+F9+F10+F11+F12+F13+F14+F15+F16+F17+F18
A20: 9949 | B20: Total for personal portion | E20: =F6+F7+F8+F9+F10+F11+F12+F13+F14+F15+F16+F17+F18
B21: Deductible expenses (Amount A minus line 9949) | E21: =E6+E7+E8+E9+E10+E11+E12+E13+E14+E15+E16+E17+E18
A22: 9369 | B22: Net income (loss) before adjustments | E22: =E5-E21
B24: Same arithmetic as the paid file, cut to two properties. Gross rents come from the Rent Ledger; each expense line is totalled from the Expenses tab and multiplied by the property's rental share. Example figures only — invented for this sample.
